datrafilcha/__init__.py
datrafilcha/facade.py
datrafilcha/graph_functions.py
datrafilcha-0.0.9.dist-info/METADATA
datrafilcha-0.0.9.dist-info/WHEEL
datrafilcha-0.0.9.dist-info/licenses/LICENSE
datrafilcha-0.0.9.dist-info/RECORD
