Metadata-Version: 2.1
Name: datrafilcha
Version: 0.0.9
Project-URL: Homepage, https://gitlab.com/gitm1993/datrafilcha
License-File: LICENSE
Classifier: License :: OSI Approved :: MIT License
Classifier: Operating System :: OS Independent
Classifier: Programming Language :: Python :: 3
Requires-Python: >=3.7
